<PAMDataset>
  <Metadata>
    <MDI key="DataType">Generic</MDI>
  </Metadata>
  <PAMRasterBand band="1">
    <Histograms>
      <HistItem>
        <HistMin>-0.5</HistMin>
        <HistMax>240.5</HistMax>
        <BucketCount>241</BucketCount>
        <IncludeOutOfRange>1</IncludeOutOfRange>
        <Approximate>0</Approximate>
        <HistCounts>0|0|0|0|0|0|0|0|1|0|1|1|0|3|3|5|17|20|30|44|72|88|95|139|197|221|223|287|344|367|501|631|663|736|871|895|1003|1110|1169|1288|1381|1508|1629|1714|1838|1843|1979|2145|2205|2242|2304|2499|2496|2731|2935|2896|3033|3179|3260|3227|3242|3377|3374|3369|3525|3619|3676|3871|3740|3933|3989|4198|4273|4464|4544|4681|4771|4850|4961|5053|5212|5179|5201|5386|5541|5621|5774|5857|6082|6318|6205|6423|6616|6784|6924|7138|7378|7478|7618|7751|7766|7964|8153|8203|8198|8171|8331|8475|8462|8563|8572|8411|8764|8771|8785|8919|8996|8832|8992|8783|9111|9096|9219|9255|9156|8957|9192|9205|8944|8631|8294|8147|8058|7939|7409|7357|7400|6892|6606|6233|6207|5878|5685|5577|5117|4961|4620|4380|4192|3880|3858|3754|3594|3407|3320|3179|3042|2881|2842|2738|2552|2545|2293|2351|2148|2013|1916|1747|1711|1638|1648|1593|1509|1537|1465|1404|1416|1285|1253|1184|1185|1075|1001|980|922|797|829|786|708|644|642|545|573|503|567|462|435|370|333|294|267|230|219|171|172|178|131|142|141|113|112|112|97|93|69|59|67|59|51|68|61|41|40|33|19|31|32|18|15|17|8|8|15|8|6|6|3|2|0|0|2</HistCounts>
      </HistItem>
    </Histograms>
    <Metadata>
      <MDI key="RepresentationType">ATHEMATIC</MDI>
      <MDI key="STATISTICS_COVARIANCES">1139.995578231957,1070.267469232396,795.9818474534612</MDI>
      <MDI key="STATISTICS_EXCLUDEDVALUES"></MDI>
      <MDI key="STATISTICS_MAXIMUM">240</MDI>
      <MDI key="STATISTICS_MEAN">110.36389989187</MDI>
      <MDI key="STATISTICS_MINIMUM">8</MDI>
      <MDI key="STATISTICS_SKIPFACTORX">1</MDI>
      <MDI key="STATISTICS_SKIPFACTORY">1</MDI>
      <MDI key="STATISTICS_STDDEV">33.763820551471</MDI>
    </Metadata>
  </PAMRasterBand>
  <PAMRasterBand band="2">
    <Histograms>
      <HistItem>
        <HistMin>-0.5</HistMin>
        <HistMax>251.5</HistMax>
        <BucketCount>252</BucketCount>
        <IncludeOutOfRange>1</IncludeOutOfRange>
        <Approximate>0</Approximate>
        <HistCounts>0|0|0|0|0|0|0|0|0|0|0|0|0|0|0|0|0|0|0|0|0|0|0|0|0|0|0|0|0|0|0|0|1|0|1|1|2|1|17|22|36|53|74|101|134|158|187|273|266|392|500|591|550|531|604|620|602|723|730|895|958|1089|1210|1311|1577|1630|1785|1754|1789|1767|1802|1854|1968|2088|2174|2301|2415|2480|2585|2602|2618|2735|2693|2811|2740|2841|2885|2947|3002|3094|2997|3048|3261|3242|3329|3411|3463|3651|3746|3846|3977|4149|4242|4498|4712|4890|4950|4977|5044|5350|5324|5535|5671|5571|5719|5833|5865|5992|6151|6390|6656|6845|7185|7292|7461|7946|8016|8239|8307|8640|8721|8774|8851|8859|9062|9225|9373|9533|9532|9865|9829|9729|9824|9678|9881|9883|10062|9892|9983|9643|9704|9704|9587|9715|9417|9397|9349|9147|8608|8489|8041|7740|7603|7393|7153|6585|6315|6001|5621|5310|4935|4599|4441|4293|4153|3934|3706|3608|3375|3219|3037|2827|2696|2658|2514|2496|2245|2181|2075|2189|2021|1890|1900|1729|1741|1594|1593|1470|1388|1241|1251|1063|1011|932|915|797|778|700|661|631|563|556|453|438|403|330|301|263|239|239|195|192|161|146|150|140|129|87|88|82|77|54|63|43|41|41|37|26|13|15|13|14|5|1|2|1|2|2|2|0|0|1</HistCounts>
      </HistItem>
    </Histograms>
    <Metadata>
      <MDI key="RepresentationType">ATHEMATIC</MDI>
      <MDI key="STATISTICS_COVARIANCES">1070.267469232396,1055.044794876393,725.3334869039123</MDI>
      <MDI key="STATISTICS_EXCLUDEDVALUES"></MDI>
      <MDI key="STATISTICS_MAXIMUM">251</MDI>
      <MDI key="STATISTICS_MEAN">135.41121000212</MDI>
      <MDI key="STATISTICS_MINIMUM">32</MDI>
      <MDI key="STATISTICS_SKIPFACTORX">1</MDI>
      <MDI key="STATISTICS_SKIPFACTORY">1</MDI>
      <MDI key="STATISTICS_STDDEV">32.481453090593</MDI>
    </Metadata>
  </PAMRasterBand>
  <PAMRasterBand band="3">
    <Histograms>
      <HistItem>
        <HistMin>-0.5</HistMin>
        <HistMax>226.5</HistMax>
        <BucketCount>227</BucketCount>
        <IncludeOutOfRange>1</IncludeOutOfRange>
        <Approximate>0</Approximate>
        <HistCounts>0|0|0|0|0|0|0|0|0|0|0|1|1|0|1|2|1|2|5|8|7|16|11|16|26|32|37|62|68|108|107|114|153|183|218|263|299|403|473|584|644|732|909|932|983|1124|1321|1440|1593|1784|1917|2321|2477|2534|2764|2941|3173|3308|3719|3967|4047|4301|4674|5057|5369|5590|5790|5988|6264|6347|6548|7050|7467|7772|8107|8143|8585|8832|9127|9424|9685|9643|9813|10019|10403|10629|10952|11348|11476|11790|11739|11905|12115|12548|12960|13064|13057|13037|13116|13079|13151|13234|13006|12942|12739|12502|12403|11829|11521|11179|10848|10440|10198|9853|9175|8891|8433|7875|7244|6815|6495|6088|5648|5248|4842|4549|4277|4074|3799|3554|3422|3135|3101|2996|2820|2664|2509|2287|2138|2018|1853|1751|1649|1640|1489|1365|1349|1295|1210|1131|1103|1075|1063|1046|909|817|821|756|689|672|655|648|585|558|511|459|410|409|368|360|346|370|330|312|319|336|311|336|316|284|271|248|221|224|210|185|205|201|170|147|145|132|135|106|94|94|79|83|64|68|59|53|58|56|38|50|48|32|38|26|23|27|23|11|11|10|11|4|3|3|3|1|0|0|0|1|1</HistCounts>
      </HistItem>
    </Histograms>
    <Metadata>
      <MDI key="RepresentationType">ATHEMATIC</MDI>
      <MDI key="STATISTICS_COVARIANCES">795.9818474534612,725.3334869039123,614.823657921064</MDI>
      <MDI key="STATISTICS_EXCLUDEDVALUES"></MDI>
      <MDI key="STATISTICS_MAXIMUM">226</MDI>
      <MDI key="STATISTICS_MEAN">96.676927967137</MDI>
      <MDI key="STATISTICS_MINIMUM">11</MDI>
      <MDI key="STATISTICS_SKIPFACTORX">1</MDI>
      <MDI key="STATISTICS_SKIPFACTORY">1</MDI>
      <MDI key="STATISTICS_STDDEV">24.795637880907</MDI>
    </Metadata>
  </PAMRasterBand>
</PAMDataset>
