<PAMDataset>
  <Metadata>
    <MDI key="DataType">Generic</MDI>
  </Metadata>
  <PAMRasterBand band="1">
    <Histograms>
      <HistItem>
        <HistMin>-0.5</HistMin>
        <HistMax>217.5</HistMax>
        <BucketCount>218</BucketCount>
        <IncludeOutOfRange>1</IncludeOutOfRange>
        <Approximate>0</Approximate>
        <HistCounts>0|0|0|0|0|0|0|0|0|0|0|0|0|0|0|0|2|0|1|3|3|3|5|12|14|30|31|60|67|103|143|179|222|254|310|363|451|520|527|610|675|731|857|925|1019|1134|1222|1352|1400|1589|1597|1820|1926|2098|2301|2504|2611|2787|2865|3053|3192|3376|3556|3653|3907|4193|4283|4511|4806|4892|5140|5345|5581|5555|5710|5898|6142|6128|6350|6472|6666|6730|6969|7151|7220|7331|7342|7538|7491|7412|7428|7342|7339|7181|7274|7183|7200|7268|7126|7189|7490|7367|7562|7363|7469|7419|7429|7480|7466|7447|7523|7284|7310|7182|7391|7282|7179|7068|7103|7031|6952|6848|7088|6890|7024|6956|6936|6820|6855|6707|6846|6616|6772|6701|6705|6489|6507|6335|6608|6631|6477|6323|6392|6192|6128|6216|6023|5854|5620|5641|5573|5317|5099|4973|4991|4664|4522|4320|4124|3914|3877|3668|3492|3242|3251|3090|2907|2743|2671|2466|2414|2266|2227|2055|1974|1853|1661|1628|1557|1513|1341|1264|1257|1127|992|958|917|725|677|676|543|478|408|385|321|303|270|214|175|152|124|101|72|58|36|26|16|15|10|5|3|6|4|0|2|2|2|1</HistCounts>
      </HistItem>
    </Histograms>
    <Metadata>
      <MDI key="RepresentationType">ATHEMATIC</MDI>
      <MDI key="STATISTICS_COVARIANCES">1132.86872352579,982.2679317679268,1020.821594171781,0</MDI>
      <MDI key="STATISTICS_EXCLUDEDVALUES"></MDI>
      <MDI key="STATISTICS_MAXIMUM">217</MDI>
      <MDI key="STATISTICS_MEAN">112.13846371189</MDI>
      <MDI key="STATISTICS_MINIMUM">16</MDI>
      <MDI key="STATISTICS_SKIPFACTORX">1</MDI>
      <MDI key="STATISTICS_SKIPFACTORY">1</MDI>
      <MDI key="STATISTICS_STDDEV">33.658115269958</MDI>
    </Metadata>
  </PAMRasterBand>
  <PAMRasterBand band="2">
    <Histograms>
      <HistItem>
        <HistMin>-0.5</HistMin>
        <HistMax>213.5</HistMax>
        <BucketCount>214</BucketCount>
        <IncludeOutOfRange>1</IncludeOutOfRange>
        <Approximate>0</Approximate>
        <HistCounts>0|0|0|0|0|0|0|0|0|0|0|0|0|0|0|0|0|0|0|0|0|0|0|1|0|1|1|3|7|7|5|6|10|20|28|34|50|68|95|113|140|178|199|257|273|345|369|413|509|614|665|707|791|910|941|1055|1051|1146|1268|1436|1457|1584|1775|1831|1974|2159|2324|2501|2573|2699|2769|2897|3048|3180|3413|3519|3748|3965|4155|4261|4357|4502|4575|4818|5090|5113|5267|5401|5468|5717|5778|5973|6134|6150|6343|6669|6635|6902|6821|6956|7186|7136|7343|7320|7610|7384|7641|7461|7513|7432|7603|7305|7507|7547|7648|7405|7633|7736|7746|7912|7811|7829|8193|8015|8174|8268|8280|8355|8462|8565|8790|8669|8716|8961|8929|8810|8905|9053|8908|8873|8882|8536|8824|8847|8751|8582|8591|8556|8180|7917|8189|7813|7683|7672|7367|7212|7014|6842|6585|6187|5837|5673|5393|4932|4717|4413|3954|3596|3244|3070|2866|2640|2468|2167|1996|1842|1653|1533|1398|1312|1118|1052|927|814|720|675|580|470|437|324|261|230|212|131|127|89|63|43|28|20|10|11|11|5|10|1|2|1|3|1|2|0|0|1</HistCounts>
      </HistItem>
    </Histograms>
    <Metadata>
      <MDI key="RepresentationType">ATHEMATIC</MDI>
      <MDI key="STATISTICS_COVARIANCES">982.2679317679268,898.0434568256244,841.8997339404781,0</MDI>
      <MDI key="STATISTICS_EXCLUDEDVALUES"></MDI>
      <MDI key="STATISTICS_MAXIMUM">213</MDI>
      <MDI key="STATISTICS_MEAN">121.63927467249</MDI>
      <MDI key="STATISTICS_MINIMUM">23</MDI>
      <MDI key="STATISTICS_SKIPFACTORX">1</MDI>
      <MDI key="STATISTICS_SKIPFACTORY">1</MDI>
      <MDI key="STATISTICS_STDDEV">29.967373205298</MDI>
    </Metadata>
  </PAMRasterBand>
  <PAMRasterBand band="3">
    <Histograms>
      <HistItem>
        <HistMin>-0.5</HistMin>
        <HistMax>217.5</HistMax>
        <BucketCount>218</BucketCount>
        <IncludeOutOfRange>1</IncludeOutOfRange>
        <Approximate>0</Approximate>
        <HistCounts>0|0|0|0|0|0|0|0|0|0|0|0|0|0|0|0|0|0|0|0|0|0|0|0|0|0|0|0|1|3|3|6|6|18|23|28|45|71|85|120|160|188|268|315|398|510|584|681|888|1070|1127|1344|1513|1737|1961|2213|2482|2737|3021|3316|3494|3886|4255|4565|5029|5278|5762|5990|6505|6799|7206|7535|7948|8374|8728|9085|9184|9757|9912|10324|10338|10672|10613|10832|10818|10660|10752|10407|10437|10221|9895|9419|9401|9232|9019|8739|8600|8466|8269|7995|7955|7678|7827|7334|7454|7393|7386|7358|7276|7306|6993|7223|7146|7080|6901|6957|7067|6634|6800|6550|6442|6172|5957|5766|5663|5374|5410|5079|5040|4941|4945|4695|4602|4628|4501|4531|4450|4320|4272|4296|4161|4104|4208|4203|4095|3989|4119|3925|3934|3844|3726|3738|3574|3550|3488|3409|3332|3233|3204|3029|2965|2872|2774|2633|2638|2494|2370|2405|2204|2196|2051|1994|1870|1850|1674|1634|1550|1479|1366|1226|1189|1161|1074|974|893|884|720|699|623|560|536|468|389|364|306|254|231|175|175|122|118|101|75|57|54|33|26|17|15|16|5|3|2|4|1|4|0|1</HistCounts>
      </HistItem>
    </Histograms>
    <Metadata>
      <MDI key="RepresentationType">ATHEMATIC</MDI>
      <MDI key="STATISTICS_COVARIANCES">1020.821594171781,841.8997339404781,1031.311738183744,0</MDI>
      <MDI key="STATISTICS_EXCLUDEDVALUES"></MDI>
      <MDI key="STATISTICS_MAXIMUM">217</MDI>
      <MDI key="STATISTICS_MEAN">106.02913481235</MDI>
      <MDI key="STATISTICS_MINIMUM">28</MDI>
      <MDI key="STATISTICS_SKIPFACTORX">1</MDI>
      <MDI key="STATISTICS_SKIPFACTORY">1</MDI>
      <MDI key="STATISTICS_STDDEV">32.114042694493</MDI>
    </Metadata>
  </PAMRasterBand>
  <PAMRasterBand band="4">
    <Histograms>
      <HistItem>
        <HistMin>-0.5</HistMin>
        <HistMax>255.5</HistMax>
        <BucketCount>256</BucketCount>
        <IncludeOutOfRange>1</IncludeOutOfRange>
        <Approximate>0</Approximate>
        <HistCounts>0|0|0|0|0|0|0|0|0|0|0|0|0|0|0|0|0|0|0|0|0|0|0|0|0|0|0|0|0|0|0|0|0|0|0|0|0|0|0|0|0|0|0|0|0|0|0|0|0|0|0|0|0|0|0|0|0|0|0|0|0|0|0|0|0|0|0|0|0|0|0|0|0|0|0|0|0|0|0|0|0|0|0|0|0|0|0|0|0|0|0|0|0|0|0|0|0|0|0|0|0|0|0|0|0|0|0|0|0|0|0|0|0|0|0|0|0|0|0|0|0|0|0|0|0|0|0|0|0|0|0|0|0|0|0|0|0|0|0|0|0|0|0|0|0|0|0|0|0|0|0|0|0|0|0|0|0|0|0|0|0|0|0|0|0|0|0|0|0|0|0|0|0|0|0|0|0|0|0|0|0|0|0|0|0|0|0|0|0|0|0|0|0|0|0|0|0|0|0|0|0|0|0|0|0|0|0|0|0|0|0|0|0|0|0|0|0|0|0|0|0|0|0|0|0|0|0|0|0|0|0|0|0|0|0|0|0|0|0|0|0|0|0|0|0|0|0|0|0|0|0|0|0|0|0|736164</HistCounts>
      </HistItem>
    </Histograms>
    <Metadata>
      <MDI key="RepresentationType">ATHEMATIC</MDI>
      <MDI key="STATISTICS_COVARIANCES">0,0,0,0</MDI>
      <MDI key="STATISTICS_EXCLUDEDVALUES"></MDI>
      <MDI key="STATISTICS_MAXIMUM">255</MDI>
      <MDI key="STATISTICS_MEAN">255</MDI>
      <MDI key="STATISTICS_MINIMUM">255</MDI>
      <MDI key="STATISTICS_SKIPFACTORX">1</MDI>
      <MDI key="STATISTICS_SKIPFACTORY">1</MDI>
      <MDI key="STATISTICS_STDDEV">0</MDI>
    </Metadata>
  </PAMRasterBand>
</PAMDataset>
