<PAMDataset>
  <Metadata>
    <MDI key="DataType">Generic</MDI>
  </Metadata>
  <PAMRasterBand band="1">
    <Histograms>
      <HistItem>
        <HistMin>-0.5</HistMin>
        <HistMax>254.5</HistMax>
        <BucketCount>255</BucketCount>
        <IncludeOutOfRange>1</IncludeOutOfRange>
        <Approximate>0</Approximate>
        <HistCounts>104|219|290|363|456|528|679|876|1022|1179|1459|1688|1977|2165|2558|3037|3462|3957|4370|4897|5308|5677|6069|6340|6795|7144|7343|7568|7627|7915|8017|7826|8017|8081|8197|8035|8245|8318|8137|8279|8223|8134|8318|8068|8320|8392|8630|8265|8299|8515|8683|8416|8570|8595|8489|8579|8639|8891|8793|8973|9024|9141|9292|9345|9299|9373|9453|9674|9623|9655|9809|9721|9825|9963|9820|9938|10014|9787|10038|10049|9987|9884|9990|10043|9816|9964|10101|10093|9924|9911|9721|9940|9991|9946|9911|10021|9847|9824|9864|9884|9672|9900|9766|9580|9896|9946|9718|9797|9668|9846|9847|9946|9813|9891|9920|9773|9928|9888|9978|9959|10079|9844|10123|9826|10182|10164|10078|10205|10147|10090|9924|10067|10143|10031|10134|10227|10008|10061|10222|9886|10205|9993|10052|9965|10099|10022|10082|9831|9864|9901|9900|9920|9983|9965|9756|9903|9817|9735|9734|9597|9589|9524|9586|9528|9313|9381|9035|9073|8973|8830|8711|8705|8518|8399|8266|8228|8174|7938|7866|7811|7698|7464|7416|7246|7141|6647|6997|6666|6545|6290|6286|6248|5919|5771|5582|5561|5362|5180|5101|4916|4775|4529|4318|4075|3952|3794|3477|3342|3332|2987|2748|2650|2433|2305|2076|1937|1797|1645|1611|1410|1293|1198|1153|1005|906|796|736|686|643|579|512|450|428|364|349|346|269|264|237|190|155|139|128|110|95|83|51|53|38|51|40|25|19|12|2</HistCounts>
      </HistItem>
    </Histograms>
    <Metadata>
      <MDI key="RepresentationType">ATHEMATIC</MDI>
      <MDI key="STATISTICS_COVARIANCES">2839.680878284584,3088.223775201799,2132.452081050303,0</MDI>
      <MDI key="STATISTICS_EXCLUDEDVALUES"></MDI>
      <MDI key="STATISTICS_MAXIMUM">254</MDI>
      <MDI key="STATISTICS_MEAN">111.12035545714</MDI>
      <MDI key="STATISTICS_MINIMUM">0</MDI>
      <MDI key="STATISTICS_SKIPFACTORX">1</MDI>
      <MDI key="STATISTICS_SKIPFACTORY">1</MDI>
      <MDI key="STATISTICS_STDDEV">53.288656187641</MDI>
    </Metadata>
  </PAMRasterBand>
  <PAMRasterBand band="2">
    <Histograms>
      <HistItem>
        <HistMin>-0.5</HistMin>
        <HistMax>255.5</HistMax>
        <BucketCount>256</BucketCount>
        <IncludeOutOfRange>1</IncludeOutOfRange>
        <Approximate>0</Approximate>
        <HistCounts>4|12|15|25|26|24|38|49|70|95|139|175|223|310|375|447|555|612|716|867|1045|1219|1413|1699|1957|2275|2614|3048|3318|3729|3849|3963|4052|3972|4160|4451|4665|4920|4882|5061|5050|5196|5285|5530|5580|5604|5968|5870|6002|5953|5966|5907|6033|6106|6056|6127|6213|6146|6140|6226|6087|6200|6129|6179|6217|6518|6373|6236|6300|6421|6582|6661|6472|6604|6598|6744|6740|6929|6947|7013|6970|7004|7086|7133|7359|7399|7412|7375|7576|7687|7907|7934|7964|7790|7934|8048|8179|8030|8220|8141|8346|8393|8532|8426|8418|8652|8727|8465|8592|8504|8652|8695|8789|8852|8786|8797|8729|8843|8847|8854|9013|8840|8998|8928|8859|8943|8891|9109|9043|8937|9096|9212|9096|9148|9047|9156|9119|9201|9134|9383|9356|9439|9447|9392|9523|9418|9482|9472|9606|9739|9689|9887|9750|9787|9571|9754|9650|9677|10047|9721|9626|9865|9806|9845|9751|9910|9707|9781|9748|9669|9776|9642|9560|9588|9661|9631|9592|9431|9557|9178|9384|9465|9267|9325|9147|9284|9356|9293|8988|9082|9051|9027|8936|8793|8697|8783|8605|8695|8530|8358|8410|8278|8203|8067|8039|7971|7901|7741|7642|7602|7508|7490|7473|7196|7080|7057|7030|6799|6822|6390|6522|6475|6348|6179|6364|6135|6015|6062|5999|5731|5846|5845|5832|5795|5804|5653|5722|5612|5841|5659|5722|5374|5473|5178|4891|4677|4267|3699|3431|2963|2603|2237|1962|1631|819|61</HistCounts>
      </HistItem>
    </Histograms>
    <Metadata>
      <MDI key="RepresentationType">ATHEMATIC</MDI>
      <MDI key="STATISTICS_COVARIANCES">3088.223775201799,3477.761066248692,2298.888705034936,0</MDI>
      <MDI key="STATISTICS_EXCLUDEDVALUES"></MDI>
      <MDI key="STATISTICS_MAXIMUM">255</MDI>
      <MDI key="STATISTICS_MEAN">140.57134432726</MDI>
      <MDI key="STATISTICS_MINIMUM">0</MDI>
      <MDI key="STATISTICS_SKIPFACTORX">1</MDI>
      <MDI key="STATISTICS_SKIPFACTORY">1</MDI>
      <MDI key="STATISTICS_STDDEV">58.972545020956</MDI>
    </Metadata>
  </PAMRasterBand>
  <PAMRasterBand band="3">
    <Histograms>
      <HistItem>
        <HistMin>-0.5</HistMin>
        <HistMax>250.5</HistMax>
        <BucketCount>251</BucketCount>
        <IncludeOutOfRange>1</IncludeOutOfRange>
        <Approximate>0</Approximate>
        <HistCounts>96|204|312|368|486|642|789|900|1195|1323|1505|1876|2053|2145|2490|2949|3092|3539|3846|4298|4968|5476|6015|6664|7466|7921|8654|9125|9467|9760|10095|10408|10673|11011|11175|11345|11423|11535|11828|12144|11737|11939|12096|12087|12468|12208|12582|12524|12444|12410|12656|12948|12748|12776|13028|13214|13172|13371|13437|13755|13767|13749|13952|13942|14194|14108|14112|14363|14355|14540|14399|14606|14513|14377|14543|14486|14316|14434|14561|14462|14335|14393|14246|14234|14360|14239|14162|14248|14157|14172|13890|13953|14056|13876|13845|13646|13588|13753|13351|13659|13475|13402|13263|13176|12992|13016|13075|12897|12867|12645|12585|12373|12451|12558|11966|11980|11733|11583|11609|11441|11363|11422|11092|10981|10986|10765|10821|10556|10395|10135|10083|9659|9698|9582|9451|9309|9022|8951|8830|8695|8369|8457|8122|8032|7661|7553|7356|7340|7034|6995|6586|6595|6244|6144|5859|5815|5684|5284|5083|4896|4709|4535|4355|4272|3929|3698|3631|3415|3354|3143|3042|2713|2610|2435|2386|2315|2202|1994|1933|1791|1662|1560|1399|1412|1237|1226|1131|1016|1044|876|865|810|774|668|647|655|572|516|530|471|441|413|393|369|319|301|287|280|240|203|234|185|152|171|160|149|137|121|120|120|83|80|85|72|83|68|49|48|38|49|36|44|31|21|19|23|25|17|19|9|14|17|7|13|9|7|6|0|4|0|1</HistCounts>
      </HistItem>
    </Histograms>
    <Metadata>
      <MDI key="RepresentationType">ATHEMATIC</MDI>
      <MDI key="STATISTICS_COVARIANCES">2132.452081050303,2298.888705034936,1716.350376981948,0</MDI>
      <MDI key="STATISTICS_EXCLUDEDVALUES"></MDI>
      <MDI key="STATISTICS_MAXIMUM">250</MDI>
      <MDI key="STATISTICS_MEAN">88.910822795871</MDI>
      <MDI key="STATISTICS_MINIMUM">0</MDI>
      <MDI key="STATISTICS_SKIPFACTORX">1</MDI>
      <MDI key="STATISTICS_SKIPFACTORY">1</MDI>
      <MDI key="STATISTICS_STDDEV">41.428859228585</MDI>
    </Metadata>
  </PAMRasterBand>
  <PAMRasterBand band="4">
    <Histograms>
      <HistItem>
        <HistMin>-0.5</HistMin>
        <HistMax>255.5</HistMax>
        <BucketCount>256</BucketCount>
        <IncludeOutOfRange>1</IncludeOutOfRange>
        <Approximate>0</Approximate>
        <HistCounts>0|0|0|0|0|0|0|0|0|0|0|0|0|0|0|0|0|0|0|0|0|0|0|0|0|0|0|0|0|0|0|0|0|0|0|0|0|0|0|0|0|0|0|0|0|0|0|0|0|0|0|0|0|0|0|0|0|0|0|0|0|0|0|0|0|0|0|0|0|0|0|0|0|0|0|0|0|0|0|0|0|0|0|0|0|0|0|0|0|0|0|0|0|0|0|0|0|0|0|0|0|0|0|0|0|0|0|0|0|0|0|0|0|0|0|0|0|0|0|0|0|0|0|0|0|0|0|0|0|0|0|0|0|0|0|0|0|0|0|0|0|0|0|0|0|0|0|0|0|0|0|0|0|0|0|0|0|0|0|0|0|0|0|0|0|0|0|0|0|0|0|0|0|0|0|0|0|0|0|0|0|0|0|0|0|0|0|0|0|0|0|0|0|0|0|0|0|0|0|0|0|0|0|0|0|0|0|0|0|0|0|0|0|0|0|0|0|0|0|0|0|0|0|0|0|0|0|0|0|0|0|0|0|0|0|0|0|0|0|0|0|0|0|0|0|0|0|0|0|0|0|0|0|0|0|1716100</HistCounts>
      </HistItem>
    </Histograms>
    <Metadata>
      <MDI key="RepresentationType">ATHEMATIC</MDI>
      <MDI key="STATISTICS_COVARIANCES">0,0,0,0</MDI>
      <MDI key="STATISTICS_EXCLUDEDVALUES"></MDI>
      <MDI key="STATISTICS_MAXIMUM">255</MDI>
      <MDI key="STATISTICS_MEAN">255</MDI>
      <MDI key="STATISTICS_MINIMUM">255</MDI>
      <MDI key="STATISTICS_SKIPFACTORX">1</MDI>
      <MDI key="STATISTICS_SKIPFACTORY">1</MDI>
      <MDI key="STATISTICS_STDDEV">0</MDI>
    </Metadata>
  </PAMRasterBand>
</PAMDataset>
