<PAMDataset>
  <Metadata>
    <MDI key="DataType">Generic</MDI>
  </Metadata>
  <PAMRasterBand band="1">
    <Histograms>
      <HistItem>
        <HistMin>-0.5</HistMin>
        <HistMax>205.5</HistMax>
        <BucketCount>206</BucketCount>
        <IncludeOutOfRange>1</IncludeOutOfRange>
        <Approximate>0</Approximate>
        <HistCounts>0|0|0|0|0|0|0|0|0|0|0|0|0|0|0|0|0|0|0|0|4|10|8|25|76|104|167|222|296|335|366|452|510|653|786|867|887|984|1087|1198|1263|1340|1410|1543|1560|1584|1687|1825|1744|1920|1911|1859|1855|1845|1867|1816|1821|1793|1924|1820|1960|1951|2007|1968|1955|2035|2039|2066|2086|2174|2172|2149|2299|2382|2361|2374|2395|2383|2443|2551|2577|2583|2676|2614|2787|2822|3058|3146|3191|3306|3299|3510|3553|3744|3695|4076|4090|4191|4444|4534|4740|4809|5047|5142|5526|5597|5821|6102|6418|6565|6992|7362|7508|7974|8125|8482|8789|9292|9439|9667|10161|10328|10684|10845|11192|11403|11605|11746|11711|12054|11829|11972|11943|11715|11792|11462|11173|10932|10661|10433|10058|9722|9454|9229|8758|8192|7919|7630|7290|6961|6410|6141|5730|5446|5167|4710|4523|4161|3868|3606|3420|3082|2959|2753|2470|2235|2051|1906|1753|1567|1398|1322|1097|1048|901|829|743|665|570|495|394|301|278|224|222|141|102|105|88|75|71|47|40|37|16|16|18|13|6|5|3|3|3|2|2|2</HistCounts>
      </HistItem>
    </Histograms>
    <Metadata>
      <MDI key="RepresentationType">ATHEMATIC</MDI>
      <MDI key="STATISTICS_COVARIANCES">927.6591258567848,904.5506215142154,627.0195751566026,0</MDI>
      <MDI key="STATISTICS_EXCLUDEDVALUES"></MDI>
      <MDI key="STATISTICS_MAXIMUM">205</MDI>
      <MDI key="STATISTICS_MEAN">118.47086209618</MDI>
      <MDI key="STATISTICS_MINIMUM">20</MDI>
      <MDI key="STATISTICS_SKIPFACTORX">1</MDI>
      <MDI key="STATISTICS_SKIPFACTORY">1</MDI>
      <MDI key="STATISTICS_STDDEV">30.457497038608</MDI>
    </Metadata>
  </PAMRasterBand>
  <PAMRasterBand band="2">
    <Histograms>
      <HistItem>
        <HistMin>-0.5</HistMin>
        <HistMax>219.5</HistMax>
        <BucketCount>220</BucketCount>
        <IncludeOutOfRange>1</IncludeOutOfRange>
        <Approximate>0</Approximate>
        <HistCounts>0|0|0|0|0|0|0|0|0|0|0|0|0|0|0|0|0|0|0|0|0|0|0|0|0|0|1|1|4|5|10|41|95|91|100|116|158|235|255|298|355|439|472|480|593|651|761|914|983|1126|1073|1127|1171|1318|1443|1437|1522|1537|1606|1605|1714|1772|1775|1701|1613|1715|1650|1665|1739|1706|1726|1672|1793|1846|1975|1859|1948|1924|2043|2022|1982|2070|2081|2117|2112|2160|2308|2296|2356|2303|2421|2365|2404|2523|2495|2507|2679|2688|2854|2889|2966|3030|3153|3154|3328|3369|3520|3563|3695|3779|4006|4013|4232|4468|4586|4637|4781|5071|5077|5350|5728|5833|6045|6274|6602|6826|7149|7646|7805|8102|8577|8967|9426|9623|10029|10222|10689|10976|11122|11673|11843|12182|12346|12392|12798|12879|12813|12806|12624|12622|12328|12415|11923|11651|11209|11156|10428|10172|9791|9273|8662|8062|7746|7057|6634|6239|5656|5159|4704|4337|3988|3681|3442|3131|2682|2416|2173|1969|1832|1564|1362|1237|1110|956|783|650|592|464|391|319|249|195|169|122|107|81|77|58|39|39|30|26|23|16|21|11|11|11|9|8|7|6|5|1|2|3|0|1|1|1</HistCounts>
      </HistItem>
    </Histograms>
    <Metadata>
      <MDI key="RepresentationType">ATHEMATIC</MDI>
      <MDI key="STATISTICS_COVARIANCES">904.5506215142154,913.5406712800616,589.3416331483925,0</MDI>
      <MDI key="STATISTICS_EXCLUDEDVALUES"></MDI>
      <MDI key="STATISTICS_MAXIMUM">219</MDI>
      <MDI key="STATISTICS_MEAN">131.63723841919</MDI>
      <MDI key="STATISTICS_MINIMUM">26</MDI>
      <MDI key="STATISTICS_SKIPFACTORX">1</MDI>
      <MDI key="STATISTICS_SKIPFACTORY">1</MDI>
      <MDI key="STATISTICS_STDDEV">30.224835339172</MDI>
    </Metadata>
  </PAMRasterBand>
  <PAMRasterBand band="3">
    <Histograms>
      <HistItem>
        <HistMin>-0.5</HistMin>
        <HistMax>210.5</HistMax>
        <BucketCount>211</BucketCount>
        <IncludeOutOfRange>1</IncludeOutOfRange>
        <Approximate>0</Approximate>
        <HistCounts>0|0|0|0|0|0|0|0|0|0|1|0|0|2|1|2|5|3|6|8|12|12|26|33|37|47|71|85|131|187|203|269|329|430|537|662|772|920|967|1230|1177|1351|1496|1677|1877|2020|2258|2521|2742|3024|3180|3280|3330|3523|3575|3654|3531|3510|3646|3700|3825|3971|4086|4319|4308|4537|4620|4999|5101|5265|5597|5787|5924|6273|6564|7018|7322|7747|8246|8530|8876|9361|9854|10119|10497|10981|11385|12004|12092|12465|12748|13089|13205|13502|13567|13350|13290|13282|12944|12979|12517|12358|12201|11668|11189|10912|10350|10152|9886|9229|8829|8450|8142|7540|7335|7032|6736|6490|6154|6008|5595|5427|5098|4719|4490|4277|3947|3704|3495|3309|3064|2895|2761|2623|2467|2376|2198|2176|1899|1871|1770|1575|1519|1457|1266|1299|1136|1075|975|940|809|825|697|692|662|619|592|506|485|450|388|316|317|322|317|273|234|209|196|173|150|135|128|100|101|77|69|54|60|48|44|39|35|29|19|19|19|14|15|5|10|1|4|7|5|3|6|2|2|5|0|0|1|0|1|0|1|0|0|0|1</HistCounts>
      </HistItem>
    </Histograms>
    <Metadata>
      <MDI key="RepresentationType">ATHEMATIC</MDI>
      <MDI key="STATISTICS_COVARIANCES">627.0195751566026,589.3416331483925,580.796942163843,0</MDI>
      <MDI key="STATISTICS_EXCLUDEDVALUES"></MDI>
      <MDI key="STATISTICS_MAXIMUM">210</MDI>
      <MDI key="STATISTICS_MEAN">93.836409817527</MDI>
      <MDI key="STATISTICS_MINIMUM">10</MDI>
      <MDI key="STATISTICS_SKIPFACTORX">1</MDI>
      <MDI key="STATISTICS_SKIPFACTORY">1</MDI>
      <MDI key="STATISTICS_STDDEV">24.099729089013</MDI>
    </Metadata>
  </PAMRasterBand>
  <PAMRasterBand band="4">
    <Histograms>
      <HistItem>
        <HistMin>-0.5</HistMin>
        <HistMax>255.5</HistMax>
        <BucketCount>256</BucketCount>
        <IncludeOutOfRange>1</IncludeOutOfRange>
        <Approximate>0</Approximate>
        <HistCounts>0|0|0|0|0|0|0|0|0|0|0|0|0|0|0|0|0|0|0|0|0|0|0|0|0|0|0|0|0|0|0|0|0|0|0|0|0|0|0|0|0|0|0|0|0|0|0|0|0|0|0|0|0|0|0|0|0|0|0|0|0|0|0|0|0|0|0|0|0|0|0|0|0|0|0|0|0|0|0|0|0|0|0|0|0|0|0|0|0|0|0|0|0|0|0|0|0|0|0|0|0|0|0|0|0|0|0|0|0|0|0|0|0|0|0|0|0|0|0|0|0|0|0|0|0|0|0|0|0|0|0|0|0|0|0|0|0|0|0|0|0|0|0|0|0|0|0|0|0|0|0|0|0|0|0|0|0|0|0|0|0|0|0|0|0|0|0|0|0|0|0|0|0|0|0|0|0|0|0|0|0|0|0|0|0|0|0|0|0|0|0|0|0|0|0|0|0|0|0|0|0|0|0|0|0|0|0|0|0|0|0|0|0|0|0|0|0|0|0|0|0|0|0|0|0|0|0|0|0|0|0|0|0|0|0|0|0|0|0|0|0|0|0|0|0|0|0|0|0|0|0|0|0|0|0|690561</HistCounts>
      </HistItem>
    </Histograms>
    <Metadata>
      <MDI key="RepresentationType">ATHEMATIC</MDI>
      <MDI key="STATISTICS_COVARIANCES">0,0,0,0</MDI>
      <MDI key="STATISTICS_EXCLUDEDVALUES"></MDI>
      <MDI key="STATISTICS_MAXIMUM">255</MDI>
      <MDI key="STATISTICS_MEAN">255</MDI>
      <MDI key="STATISTICS_MINIMUM">255</MDI>
      <MDI key="STATISTICS_SKIPFACTORX">1</MDI>
      <MDI key="STATISTICS_SKIPFACTORY">1</MDI>
      <MDI key="STATISTICS_STDDEV">0</MDI>
    </Metadata>
  </PAMRasterBand>
</PAMDataset>
